{
  "id": "SYS_022",
  "client": "广州地铁地产",
  "context": "广州地铁生产环境",
  "systemName": "桩基验收体系",
  "date": "20260130",
  "filename": "广州地铁地产-PROD(广州地铁生产环境)桩基验收体系-20260130.xls",
  "originalHeader": [
    "序号",
    "分部名称",
    "子分部名称",
    "分项名称"
  ],
  "keys": [
    "1",
    "CateName",
    "SubCateName",
    "LibName"
  ],
  "content": [
    {
      "1": "2",
      "CateName": "桩基",
      "SubCateName": "单桩",
      "LibName": "静压管桩"
    },
    {
      "1": "3",
      "CateName": "桩基",
      "SubCateName": "单桩",
      "LibName": "锤击管桩"
    },
    {
      "1": "4",
      "CateName": "桩基",
      "SubCateName": "单桩",
      "LibName": "灌注桩"
    },
    {
      "1": "5",
      "CateName": "桩基",
      "SubCateName": "单桩",
      "LibName": "搅拌桩"
    },
    {
      "1": "6",
      "CateName": "桩基",
      "SubCateName": "单桩",
      "LibName": "锚杆桩"
    },
    {
      "1": "7",
      "CateName": "桩基",
      "SubCateName": "单桩",
      "LibName": "CFG桩"
    }
  ]
}