{
  "id": "SYS_042",
  "client": "深铁置业",
  "context": "深铁置业-集团云PROD",
  "systemName": "工序移交体系",
  "date": "20260130",
  "filename": "深铁置业-PROD(深铁置业-集团云PROD)工序移交体系-20260130.xls",
  "originalHeader": [
    "序号",
    "工序名称",
    "指标名称"
  ],
  "keys": [
    "1",
    "CateName",
    "LibraryName"
  ],
  "content": [
    {
      "1": "2",
      "CateName": "基坑支护单位向土方单位移交基坑支护阶段性完工工作面",
      "LibraryName": "1) 基坑支护已按照设计及合同要求施工完成;"
    },
    {
      "1": "3",
      "CateName": "基坑支护单位向土方单位移交基坑支护阶段性完工工作面",
      "LibraryName": "2) 场地基坑监测数据在控制范围内;"
    },
    {
      "1": "4",
      "CateName": "基坑支护单位向土方单位移交基坑支护阶段性完工工作面",
      "LibraryName": "3) 已具备土方分层开挖条件。"
    },
    {
      "1": "5",
      "CateName": "土方/基坑支护单位向桩基础移交桩基础施工作面",
      "LibraryName": "1) 土方已按照图纸及合同要求开挖至指定标高;"
    },
    {
      "1": "6",
      "CateName": "土方/基坑支护单位向桩基础移交桩基础施工作面",
      "LibraryName": "2) 土方完成面标高误差是满足规范要求："
    },
    {
      "1": "7",
      "CateName": "土方/基坑支护单位向桩基础移交桩基础施工作面",
      "LibraryName": "3) 基坑支护已完成设计及合同内施工内容；"
    },
    {
      "1": "8",
      "CateName": "土方/基坑支护单位向桩基础移交桩基础施工作面",
      "LibraryName": "4) 基坑四周边线清晰,与图纸相符合;"
    },
    {
      "1": "9",
      "CateName": "土方/基坑支护单位向桩基础移交桩基础施工作面",
      "LibraryName": "5) 基坑底部及基坑底部四周降排水措施齐全;"
    },
    {
      "1": "10",
      "CateName": "土方/基坑支护单位向桩基础移交桩基础施工作面",
      "LibraryName": "6）基坑监测数据稳定，在控制范围内。"
    },
    {
      "1": "11",
      "CateName": "桩基础单位向总包单位移交桩基础完工工作面",
      "LibraryName": "1) 基础桩无遗漏，符合设计要求;"
    },
    {
      "1": "12",
      "CateName": "桩基础单位向总包单位移交桩基础完工工作面",
      "LibraryName": "2) 桩点位置准确，符合设计及规范要求;"
    },
    {
      "1": "13",
      "CateName": "桩基础单位向总包单位移交桩基础完工工作面",
      "LibraryName": "3) 桩身完整性、单桩承载力数据满足设计及规范要求；"
    },
    {
      "1": "14",
      "CateName": "桩基础单位向总包单位移交桩基础完工工作面",
      "LibraryName": "4) 桩基础标高及桩头钢筋锚固长度符合设计及规范要求。"
    },
    {
      "1": "15",
      "CateName": "总包单位/防火门单位向变配电单位/机电单位/消防单位移交地下室设备用房工作面",
      "LibraryName": "1) 天棚墙面涂料、地面找平施工完成；"
    },
    {
      "1": "16",
      "CateName": "总包单位/防火门单位向变配电单位/机电单位/消防单位移交地下室设备用房工作面",
      "LibraryName": "2) 底板、顶板、地下室外墙无渗漏情况；"
    },
    {
      "1": "17",
      "CateName": "总包单位/防火门单位向变配电单位/机电单位/消防单位移交地下室设备用房工作面",
      "LibraryName": "3) 集水井、排水沟施工完成、排水系统通畅；"
    },
    {
      "1": "18",
      "CateName": "总包单位/防火门单位向变配电单位/机电单位/消防单位移交地下室设备用房工作面",
      "LibraryName": "4) 桥架、机电等预留洞口预留准确；"
    },
    {
      "1": "19",
      "CateName": "总包单位/防火门单位向变配电单位/机电单位/消防单位移交地下室设备用房工作面",
      "LibraryName": "5) 防火门安装完成；（若大型设备，可先完成设备进场及安装再行施工后施工墙面及防火门）"
    },
    {
      "1": "20",
      "CateName": "总包单位/防火门单位向变配电单位/机电单位/消防单位移交地下室设备用房工作面",
      "LibraryName": "6）室内照明满足施工要求。"
    },
    {
      "1": "21",
      "CateName": "结构班组向砌体班组移交砌体工程工作面",
      "LibraryName": "1) 移交部位已按结构设计要求施工完毕；"
    },
    {
      "1": "22",
      "CateName": "结构班组向砌体班组移交砌体工程工作面",
      "LibraryName": "2) 墙体表面平整度、垂直度、截面尺寸、楼板水平度和厚度满足集团综合评估标准要求；"
    },
    {
      "1": "23",
      "CateName": "结构班组向砌体班组移交砌体工程工作面",
      "LibraryName": "3) 卫生间、露台等部位的防水反坎按要求完成；"
    },
    {
      "1": "24",
      "CateName": "结构班组向砌体班组移交砌体工程工作面",
      "LibraryName": "4) 所有临边洞口防护完成；"
    },
    {
      "1": "25",
      "CateName": "结构班组向砌体班组移交砌体工程工作面",
      "LibraryName": "5) 所有垃圾清理完成；"
    },
    {
      "1": "26",
      "CateName": "结构班组向砌体班组移交砌体工程工作面",
      "LibraryName": "6) 模板、对拉螺栓拆除完毕；"
    },
    {
      "1": "27",
      "CateName": "结构班组向砌体班组移交砌体工程工作面",
      "LibraryName": "7) 水电安装预留管洞处理完成；"
    },
    {
      "1": "28",
      "CateName": "结构班组向砌体班组移交砌体工程工作面",
      "LibraryName": "8) 每户墙定位线完成，方正控制线完成，监理验收完成。"
    },
    {
      "1": "29",
      "CateName": "总包单位向各分包移交建筑一米线",
      "LibraryName": "1）公共区域建筑一米线标识，包括建筑一米线线条清晰顺直，建筑一米线文字标识清晰，有具体标高标识；"
    },
    {
      "1": "30",
      "CateName": "总包单位向各分包移交建筑一米线",
      "LibraryName": "2）室内部分建筑一米线墨线清晰顺直，各个功能房间均有建筑一米线；"
    },
    {
      "1": "31",
      "CateName": "总包单位向各分包移交建筑一米线",
      "LibraryName": "3）室内标高原始引入点标识清晰，可通过原始引入点核对室内标高是否有误；"
    },
    {
      "1": "32",
      "CateName": "总包单位向各分包移交建筑一米线",
      "LibraryName": "4）基准进出线、洞口中心线标识清晰顺直。"
    },
    {
      "1": "33",
      "CateName": "砌体班组向移交机电单位机电安装工作面",
      "LibraryName": "1）移交部位砌体、顶砌、二次构件已按照图纸施工完成；"
    },
    {
      "1": "34",
      "CateName": "砌体班组向移交机电单位机电安装工作面",
      "LibraryName": "2）现场垃圾清理完成；"
    },
    {
      "1": "35",
      "CateName": "砌体班组向移交机电单位机电安装工作面",
      "LibraryName": "3）所有临边洞口防护恢复完成；"
    },
    {
      "1": "36",
      "CateName": "砌体班组向移交机电单位机电安装工作面",
      "LibraryName": "4）现场垃圾清理完成；"
    },
    {
      "1": "37",
      "CateName": "砌体班组向移交机电单位机电安装工作面",
      "LibraryName": "5）所有临边洞口防护恢复完成。"
    },
    {
      "1": "38",
      "CateName": "结构/砌体/机电单位向抹灰移交抹灰工程工作面",
      "LibraryName": "1) 砌体：移交部位已按设计要求施工完毕；"
    },
    {
      "1": "39",
      "CateName": "结构/砌体/机电单位向抹灰移交抹灰工程工作面",
      "LibraryName": "2) 砌体：砌体表面平整度、垂直度满足实测实量要求；"
    },
    {
      "1": "40",
      "CateName": "结构/砌体/机电单位向抹灰移交抹灰工程工作面",
      "LibraryName": "3) 砌体：窗台板：宽同墙厚，高度≥100mm，每边入墙内≥240mm（不足240mm通长设置）；"
    },
    {
      "1": "41",
      "CateName": "结构/砌体/机电单位向抹灰移交抹灰工程工作面",
      "LibraryName": "4) 砌体：混砌：除斜顶砖、下槛和其他预制块外，无混砌现象；"
    },
    {
      "1": "42",
      "CateName": "结构/砌体/机电单位向抹灰移交抹灰工程工作面",
      "LibraryName": "5) 砌体：灰缝无瞎缝、透缝、通缝，双面勾缝、灰缝要密实；"
    },
    {
      "1": "43",
      "CateName": "结构/砌体/机电单位向抹灰移交抹灰工程工作面",
      "LibraryName": "6) 砌体：二次结构：构造柱、窗台板、防水反坎等二次结构浇筑密实，无蜂窝、露筋、夹渣、开裂等质量缺陷；二次结构螺杆洞已封堵完成；"
    },
    {
      "1": "44",
      "CateName": "结构/砌体/机电单位向抹灰移交抹灰工程工作面",
      "LibraryName": "7) 砌体：砌体无污染、无破损；"
    },
    {
      "1": "45",
      "CateName": "结构/砌体/机电单位向抹灰移交抹灰工程工作面",
      "LibraryName": "8) 结构；内外墙螺杆洞封堵完成、混凝土质量缺陷整改完成；"
    },
    {
      "1": "46",
      "CateName": "结构/砌体/机电单位向抹灰移交抹灰工程工作面",
      "LibraryName": "9) 机电；机电线盒管线预埋完成，固定方式正确，线盒标高差无误、对开凿过程中破坏的墙体已经完成修补；"
    },
    {
      "1": "47",
      "CateName": "结构/砌体/机电单位向抹灰移交抹灰工程工作面",
      "LibraryName": "10）机电：机电施工完成后场地清理完成；"
    },
    {
      "1": "48",
      "CateName": "总包向机电/消防单位移交公区管井施工工作面",
      "LibraryName": "1、按照设计要求管井内砌体、抹灰、墙体大白等施工；"
    },
    {
      "1": "49",
      "CateName": "总包向机电/消防单位移交公区管井施工工作面",
      "LibraryName": "2、管井内垃圾清理完毕；"
    },
    {
      "1": "50",
      "CateName": "总包向机电/消防单位移交公区管井施工工作面",
      "LibraryName": "3、消火栓、桥架等洞口按照设计预留、尺寸符合要求。"
    },
    {
      "1": "51",
      "CateName": "机电/消防单位向总包移交管井收口工作面",
      "LibraryName": "1）管井内给排水、桥架等管道安装完毕；"
    },
    {
      "1": "52",
      "CateName": "机电/消防单位向总包移交管井收口工作面",
      "LibraryName": "2）管道、桥架按照要求固定牢固；"
    },
    {
      "1": "53",
      "CateName": "机电/消防单位向总包移交管井收口工作面",
      "LibraryName": "3）管井内垃圾清理完毕；"
    },
    {
      "1": "54",
      "CateName": "机电/消防单位向总包移交管井收口工作面",
      "LibraryName": "4）管井具备吊洞封口，施工地坪的条件；"
    },
    {
      "1": "55",
      "CateName": "机电/消防单位向总包移交管井收口工作面",
      "LibraryName": "5）消火栓已按照设计要求安装和固定完毕；"
    },
    {
      "1": "56",
      "CateName": "机电/消防单位向总包移交管井收口工作面",
      "LibraryName": "6）完工后场地清理干净。"
    },
    {
      "1": "57",
      "CateName": "总包向防火门单位移交防火门安装工作面",
      "LibraryName": "1) 移交部位已按照设计要求施工完毕；"
    },
    {
      "1": "58",
      "CateName": "总包向防火门单位移交防火门安装工作面",
      "LibraryName": "2) 已留置的洞口尺寸及标高符合设计要求；"
    },
    {
      "1": "59",
      "CateName": "总包向防火门单位移交防火门安装工作面",
      "LibraryName": "3) 门窗口清理干净，无污染；"
    },
    {
      "1": "60",
      "CateName": "总包向防火门单位移交防火门安装工作面",
      "LibraryName": "4) 洞口两侧设置预埋实心砖或混凝土块供门窗固定、预制块间距符合要求；"
    },
    {
      "1": "61",
      "CateName": "总包向防火门单位移交防火门安装工作面",
      "LibraryName": "5) 公区有精装修贴砖部位，防火门安装部位墙面灰饼已施工完毕，或者抹灰已经完成，具备防火门进出位控制条件；无贴砖部位，砌体已经完成施工；"
    },
    {
      "1": "62",
      "CateName": "总包向防火门单位移交防火门安装工作面",
      "LibraryName": "6) 一米线已标识。"
    },
    {
      "1": "63",
      "CateName": "防火门单位向总包单位移交防火门完成工作面",
      "LibraryName": "1) 安装位置和构造做法符合设计要求；"
    },
    {
      "1": "64",
      "CateName": "防火门单位向总包单位移交防火门完成工作面",
      "LibraryName": "2）门框安装牢固、垂直，临时固定的木质固定片清理完毕。"
    },
    {
      "1": "65",
      "CateName": "防火门单位向总包单位移交防火门完成工作面",
      "LibraryName": "3) 门扇用美纹纸或软膜满包保护；"
    },
    {
      "1": "66",
      "CateName": "防火门单位向总包单位移交防火门完成工作面",
      "LibraryName": "4) 合页安装正确；"
    },
    {
      "1": "67",
      "CateName": "防火门单位向总包单位移交防火门完成工作面",
      "LibraryName": "5) 门扇及框安装牢固，留缝均匀顺直，开启灵活、闭关严密；"
    },
    {
      "1": "68",
      "CateName": "防火门单位向总包单位移交防火门完成工作面",
      "LibraryName": "6) 门框及门扇的表面油漆颜色均匀无色差、无划伤、无凹痕等缺陷；"
    },
    {
      "1": "69",
      "CateName": "防火门单位向总包单位移交防火门完成工作面",
      "LibraryName": "7) 门锁开启灵活、门吸安装牢固、位置正确、闭门器灵活有效；"
    },
    {
      "1": "70",
      "CateName": "防火门单位向总包单位移交防火门完成工作面",
      "LibraryName": "8) 门扇表面清洁、无污迹。"
    },
    {
      "1": "71",
      "CateName": "总包单位向门窗单位移交门窗安装工程工作面",
      "LibraryName": "1) 移交部位已按照设计要求施工完毕；"
    },
    {
      "1": "72",
      "CateName": "总包单位向门窗单位移交门窗安装工程工作面",
      "LibraryName": "2) 已留置的洞口尺寸及标高符合设计要求；"
    },
    {
      "1": "73",
      "CateName": "总包单位向门窗单位移交门窗安装工程工作面",
      "LibraryName": "3) 门窗口清理干净，无污染；"
    },
    {
      "1": "74",
      "CateName": "总包单位向门窗单位移交门窗安装工程工作面",
      "LibraryName": "4) 洞口两侧设置预埋实心砖或混凝土块供门窗固定、预制块间距符合要求；"
    },
    {
      "1": "75",
      "CateName": "总包单位向门窗单位移交门窗安装工程工作面",
      "LibraryName": "5) 窗台混凝土压顶施工完毕且符合要求；"
    },
    {
      "1": "76",
      "CateName": "总包单位向门窗单位移交门窗安装工程工作面",
      "LibraryName": "6) 预留避雷接触点或避雷接触点剔打出；"
    },
    {
      "1": "77",
      "CateName": "总包单位向门窗单位移交门窗安装工程工作面",
      "LibraryName": "7) 进出基准线、洞口中心线、建筑一米线移交完成。"
    },
    {
      "1": "78",
      "CateName": "总包单位向门窗单位移交门窗安装工程工作面",
      "LibraryName": "8) 百页内土建项目施工完毕，垃圾清理完成。"
    },
    {
      "1": "79",
      "CateName": "门窗单位向总包单位移交门窗收边工程工作面",
      "LibraryName": "1) 安装位置和构造做法符合设计要求；"
    },
    {
      "1": "80",
      "CateName": "门窗单位向总包单位移交门窗收边工程工作面",
      "LibraryName": "2) 固定拉片数量和固定方式符合设计和规范要求；"
    },
    {
      "1": "81",
      "CateName": "门窗单位向总包单位移交门窗收边工程工作面",
      "LibraryName": "3) 防雷接地焊接符合设计和规范要求；"
    },
    {
      "1": "82",
      "CateName": "门窗单位向总包单位移交门窗收边工程工作面",
      "LibraryName": "4) 塞缝材料和施工工艺符合设计和规范要求；"
    },
    {
      "1": "83",
      "CateName": "门窗单位向总包单位移交门窗收边工程工作面",
      "LibraryName": "5) 外窗或阳台推拉门防水施工质量符合设计和规范要求；"
    },
    {
      "1": "84",
      "CateName": "门窗单位向总包单位移交门窗收边工程工作面",
      "LibraryName": "6) 成品保护措施到位；"
    },
    {
      "1": "85",
      "CateName": "门窗单位向总包单位移交门窗收边工程工作面",
      "LibraryName": "7) 塞缝处无残留的木楔、杂物，安装未对墙体造成损坏；"
    },
    {
      "1": "86",
      "CateName": "门窗单位向总包单位移交门窗收边工程工作面",
      "LibraryName": "8) 场内垃圾清理完成，安全防护齐全。"
    },
    {
      "1": "87",
      "CateName": "总包单位向幕墙单位移交幕墙工程工作面",
      "LibraryName": "1) 预留避雷接触点或避雷接触点剔打出；"
    },
    {
      "1": "88",
      "CateName": "总包单位向幕墙单位移交幕墙工程工作面",
      "LibraryName": "2) 标高线及进出位基准线清晰准确；"
    },
    {
      "1": "89",
      "CateName": "总包单位向幕墙单位移交幕墙工程工作面",
      "LibraryName": "3) 结构洞口尺寸偏差或外面垂直度偏差经剔凿或修补，符合幕墙施工要求；"
    },
    {
      "1": "90",
      "CateName": "总包单位向幕墙单位移交幕墙工程工作面",
      "LibraryName": "4) 预埋件有可靠位置固定，禁止固定在砖墙上（若为后锚固施工）；"
    },
    {
      "1": "91",
      "CateName": "总包单位向幕墙单位移交幕墙工程工作面",
      "LibraryName": "5) 幕墙内结构、砖砌、抹灰或者外涂饰工程施工完毕且经验收合格（根据具体图纸要求）；"
    },
    {
      "1": "92",
      "CateName": "总包单位向幕墙单位移交幕墙工程工作面",
      "LibraryName": "6) 提供安全且满足幕墙作业的外脚手架、吊篮安装工作面或临边作业可靠的安全带固定点（如单元式幕墙所需工作面）；"
    },
    {
      "1": "93",
      "CateName": "总包单位向幕墙单位移交幕墙工程工作面",
      "LibraryName": "7) 满足幕墙材料垂直转运的机械设备及材料堆码场地。"
    },
    {
      "1": "94",
      "CateName": "幕墙单位向精装单位移交幕墙工程完工工作面",
      "LibraryName": "1) 幕墙单位已按照设计要求完成；"
    },
    {
      "1": "95",
      "CateName": "幕墙单位向精装单位移交幕墙工程完工工作面",
      "LibraryName": "2) 幕墙玻璃品种、颜色符合设计要求，无翘曲、无裂纹、无划痕；"
    },
    {
      "1": "96",
      "CateName": "幕墙单位向精装单位移交幕墙工程完工工作面",
      "LibraryName": "3) 骨架型材颜色一致，无砸压变形，表面洁净，无污染，拼接严密平整，接口平滑；"
    },
    {
      "1": "97",
      "CateName": "幕墙单位向精装单位移交幕墙工程完工工作面",
      "LibraryName": "4) 耐候胶缝横竖缝的大小、宽窄一致，无错台错位。耐候胶与玻璃、铝材粘结牢固，胶缝表面平整，光滑、深浅一致；"
    },
    {
      "1": "98",
      "CateName": "幕墙单位向精装单位移交幕墙工程完工工作面",
      "LibraryName": "5) 已完成工完场清；"
    },
    {
      "1": "99",
      "CateName": "幕墙单位向精装单位移交幕墙工程完工工作面",
      "LibraryName": "6) 安全防护恢复、完备齐全。"
    },
    {
      "1": "100",
      "CateName": "幕墙单位向精装单位移交幕墙工程完工工作面",
      "LibraryName": "7）铝合金下滑保护：铝合金推拉门和平开门下滑需进行铁皮或木板硬保护放置施工破坏。"
    },
    {
      "1": "101",
      "CateName": "总包单位向栏杆单位移交栏杆安装工程工作面",
      "LibraryName": "1) 主包单位结构，砌筑，二次结构已按设计要求施工完毕；"
    },
    {
      "1": "102",
      "CateName": "总包单位向栏杆单位移交栏杆安装工程工作面",
      "LibraryName": "2) 由主包单位提供标高线，进出位基准线，标高进出位即出现符合设计要求，准确、清晰；"
    },
    {
      "1": "103",
      "CateName": "总包单位向栏杆单位移交栏杆安装工程工作面",
      "LibraryName": "3) 由主包单位提供将预留预留避雷接触点或避雷接触点剔打出；"
    },
    {
      "1": "104",
      "CateName": "总包单位向栏杆单位移交栏杆安装工程工作面",
      "LibraryName": "4) 主包单位主体及二次结构施工过程中，栏杆预埋件已按设计要求埋设完毕，位置符合设计要求；（如有）"
    },
    {
      "1": "105",
      "CateName": "总包单位向栏杆单位移交栏杆安装工程工作面",
      "LibraryName": "5) 主包单位主体及二次结构施工过程中，栏杆固定点为混凝土或已采取可靠加固措施（如预制块和实心砖），加固措施符合设计要求。（如不需埋件）"
    },
    {
      "1": "106",
      "CateName": "栏杆单位向总包单位移交栏杆安装后的工作面",
      "LibraryName": "1) 栏杆安装位置和构造做法符合要求；"
    },
    {
      "1": "107",
      "CateName": "栏杆单位向总包单位移交栏杆安装后的工作面",
      "LibraryName": "2) 埋件做法、膨胀螺栓数量，紧固程度符合要求，手摇不晃；"
    },
    {
      "1": "108",
      "CateName": "栏杆单位向总包单位移交栏杆安装后的工作面",
      "LibraryName": "3) 防雷接地位置准确，无漏焊，焊接质量符合要求；"
    },
    {
      "1": "109",
      "CateName": "栏杆单位向总包单位移交栏杆安装后的工作面",
      "LibraryName": "4) 栏杆节点以做除锈防锈处理或施工不锈钢配件："
    },
    {
      "1": "110",
      "CateName": "栏杆单位向总包单位移交栏杆安装后的工作面",
      "LibraryName": "5) 栏杆成品保护措施完备，垃圾清理干净。"
    },
    {
      "1": "111",
      "CateName": "总包单位向保温单位移交保温工程工作面",
      "LibraryName": "1) 移交部位已按设计要求施工完毕；"
    },
    {
      "1": "112",
      "CateName": "总包单位向保温单位移交保温工程工作面",
      "LibraryName": "2) 外墙层高范围垂直度偏差在4mm内；表面平整度在4mm内"
    },
    {
      "1": "113",
      "CateName": "总包单位向保温单位移交保温工程工作面",
      "LibraryName": "3) 基层外观质量无起砂、空鼓、开裂；"
    },
    {
      "1": "114",
      "CateName": "总包单位向保温单位移交保温工程工作面",
      "LibraryName": "4) 基层灰尘、油污清理完成；"
    },
    {
      "1": "115",
      "CateName": "总包单位向保温单位移交保温工程工作面",
      "LibraryName": "5) 外墙管洞处理完成；"
    },
    {
      "1": "116",
      "CateName": "总包单位向保温单位移交保温工程工作面",
      "LibraryName": "6) 安全防护到位、安全设施齐全；"
    },
    {
      "1": "117",
      "CateName": "总包单位向保温单位移交保温工程工作面",
      "LibraryName": "7) 防水涂料施工完毕，节点等细部处理符合要求；"
    },
    {
      "1": "118",
      "CateName": "总包单位向保温单位移交保温工程工作面",
      "LibraryName": "8) 垂直运输机械运转正常。"
    },
    {
      "1": "119",
      "CateName": "保温单位向外墙饰面单位移交外墙饰面工作面",
      "LibraryName": "1) 保温板、保温砂浆、抗裂网等设计要求完成施工，门窗周边构造、滴水线正确、泄水孔外露，门窗外开与线条不冲突。"
    },
    {
      "1": "120",
      "CateName": "保温单位向外墙饰面单位移交外墙饰面工作面",
      "LibraryName": "2) 抹面砂浆与聚苯板必须粘结牢固，无脱落、空鼓，网格布不得外露；"
    },
    {
      "1": "121",
      "CateName": "保温单位向外墙饰面单位移交外墙饰面工作面",
      "LibraryName": "3) 表面无爆灰、裂缝等缺陷，外观表面清洁、接错平整。"
    },
    {
      "1": "122",
      "CateName": "总包单位向防水单位移交防水工程工作面",
      "LibraryName": "1）细部处理：变形缝、后浇带、穿墙穿楼板孔洞等节点做法正确，试水不漏；基层阴阳角均做圆角处理；"
    },
    {
      "1": "123",
      "CateName": "总包单位向防水单位移交防水工程工作面",
      "LibraryName": "2）防水层的基层：基层牢固，基面洁净、平整，无积水、无空鼓、松动、起砂和脱皮现象，结构蜂窝、麻面、孔洞等缺陷修补完毕；防水基层放坡满足图纸要求。"
    },
    {
      "1": "124",
      "CateName": "总包单位向防水单位移交防水工程工作面",
      "LibraryName": "3）管道安装：应在防水层施工前安装的管道均安装完毕；"
    },
    {
      "1": "125",
      "CateName": "总包单位向防水单位移交防水工程工作面",
      "LibraryName": "4）安全防护到位；"
    },
    {
      "1": "126",
      "CateName": "总包单位向防水单位移交防水工程工作面",
      "LibraryName": "5）安全设施齐备；"
    },
    {
      "1": "127",
      "CateName": "总包单位向防水单位移交防水工程工作面",
      "LibraryName": "6）垂直运输机械运转正常；"
    },
    {
      "1": "128",
      "CateName": "总包单位向防水单位移交防水工程工作面",
      "LibraryName": "7）地下室外墙无裂缝或裂缝已处理(若为地下室外墙防水移交)；"
    },
    {
      "1": "129",
      "CateName": "总包单位向防水单位移交防水工程工作面",
      "LibraryName": "8）外墙操作架完成且搭设合理。"
    },
    {
      "1": "130",
      "CateName": "防水单位向总包单位移交防水工程完工工作面",
      "LibraryName": "1）细部处理：变形缝、后浇带、穿墙穿楼板孔洞、阴阳角等节点做法正确；"
    },
    {
      "1": "131",
      "CateName": "防水单位向总包单位移交防水工程完工工作面",
      "LibraryName": "2）防水材料、防水层厚度满足设计要求；"
    },
    {
      "1": "132",
      "CateName": "防水单位向总包单位移交防水工程完工工作面",
      "LibraryName": "3）防水施工均匀，搭接长度、搭接位置等符合要求，无起皮、空鼓等质量缺陷现象。"
    },
    {
      "1": "133",
      "CateName": "防水单位向总包单位移交防水工程完工工作面",
      "LibraryName": "4）已经过试验且无渗漏，试水及验收记录齐全。"
    },
    {
      "1": "134",
      "CateName": "屋面结构班组向砌体/机电移交屋面工程工作面",
      "LibraryName": "1) 移交部位已按照设计要求完成施工；"
    },
    {
      "1": "135",
      "CateName": "屋面结构班组向砌体/机电移交屋面工程工作面",
      "LibraryName": "2) 屋面结构表面平整垂直度满足规范要求，无裂缝，无起砂，无蜂窝麻面；"
    },
    {
      "1": "136",
      "CateName": "屋面结构班组向砌体/机电移交屋面工程工作面",
      "LibraryName": "3) 屋面结构接缝均匀顺直，结构无缺棱掉角，防水返檐预留高度（屋面结构层至泛水檐不小于500mm）、位置满足设计要求；"
    },
    {
      "1": "137",
      "CateName": "屋面结构班组向砌体/机电移交屋面工程工作面",
      "LibraryName": "4) 屋面无浮灰、混凝土块、砂浆等杂物；"
    },
    {
      "1": "138",
      "CateName": "屋面结构班组向砌体/机电移交屋面工程工作面",
      "LibraryName": "5) 出口水、檐沟、落水管安装牢固、接口封堵严密；"
    },
    {
      "1": "139",
      "CateName": "屋面结构班组向砌体/机电移交屋面工程工作面",
      "LibraryName": "6) 出屋面风道、烟道等渗漏隐患位置设置混凝土反坎（需与屋面结构一次性浇筑）。"
    },
    {
      "1": "140",
      "CateName": "总包单位/机电/智能化/消防/防火门单位向公区精装单位移交公区精装修工作面",
      "LibraryName": "1) 总包单位：砌筑、抹灰、地坪等分项工程已按设计要求施工完毕；"
    },
    {
      "1": "141",
      "CateName": "总包单位/机电/智能化/消防/防火门单位向公区精装单位移交公区精装修工作面",
      "LibraryName": "2) 总包单位；开间、尺寸、方正度、墙地面平整度、垂直度、抹灰空鼓、开裂、漏钢丝网、细部处理、顶棚露筋、顶板极差、洞口尺寸符合集团综合评估要求；"
    },
    {
      "1": "142",
      "CateName": "总包单位/机电/智能化/消防/防火门单位向公区精装单位移交公区精装修工作面",
      "LibraryName": "3) 总包单位：相应标高线已完成；"
    },
    {
      "1": "143",
      "CateName": "总包单位/机电/智能化/消防/防火门单位向公区精装单位移交公区精装修工作面",
      "LibraryName": "4) 门窗；门窗框安装完成、塞缝及收口已完成，垂直度、进出位符合综合评估要求，表面无划痕或污染；"
    },
    {
      "1": "144",
      "CateName": "总包单位/机电/智能化/消防/防火门单位向公区精装单位移交公区精装修工作面",
      "LibraryName": "5)机电：天花墙面多余线盒封堵，线盒高差、入墙深度符合要求，相关强弱电井、水井、公区管线等已完成，功能正常，吊顶内安装工程已施工、调试完毕；"
    },
    {
      "1": "145",
      "CateName": "总包单位/机电/智能化/消防/防火门单位向公区精装单位移交公区精装修工作面",
      "LibraryName": "6) 栏杆；栏杆高度符合设计要求、栏杆安装稳固；"
    },
    {
      "1": "146",
      "CateName": "总包单位/机电/智能化/消防/防火门单位向公区精装单位移交公区精装修工作面",
      "LibraryName": "7) 消防：报警器、烟感等点位施工完成、消火栓安装固定完成，尺寸、标高及进出位符合精装修要求；"
    },
    {
      "1": "147",
      "CateName": "总包单位/机电/智能化/消防/防火门单位向公区精装单位移交公区精装修工作面",
      "LibraryName": "8) 防火门框安装完成，防火门固定方式、尺寸及进出位精装修施工要求；"
    },
    {
      "1": "148",
      "CateName": "总包单位/机电/智能化/消防/防火门单位向公区精装单位移交公区精装修工作面",
      "LibraryName": "9) 各单位垃圾清理完成，各项相应成品保护已完成。"
    },
    {
      "1": "149",
      "CateName": "总包单位/机电/智能化/消防/防火门单位向公区精装单位移交公区精装修工作面",
      "LibraryName": "10) 智能化：摄像头、消防广播、穿线定位、终端设备完成；"
    },
    {
      "1": "150",
      "CateName": "总包向室内精装修单位移交土建精装修工作面",
      "LibraryName": "1）走场排查：精装修主导，四方走场排查楼层问题形成一户一表整改销项单，并签署整改完成时间。"
    },
    {
      "1": "151",
      "CateName": "总包向室内精装修单位移交土建精装修工作面",
      "LibraryName": "2）整改销项：根据一户一表对问题进行逐项整改，每日销项。"
    },
    {
      "1": "152",
      "CateName": "总包向室内精装修单位移交土建精装修工作面",
      "LibraryName": "3）场地移交：整改完毕后，四方对照一户一表复查，若无问题签署移交。"
    },
    {
      "1": "153",
      "CateName": "总包向室内精装修单位移交土建精装修工作面",
      "LibraryName": "4）为保证精装修进度，允许带病移交（不包括结构裂缝、渗漏、漏烟风险），总包承诺整改完成时间，逾期未完成由精装修代工，费用转扣。"
    },
    {
      "1": "154",
      "CateName": "总包向室内精装修单位移交土建精装修工作面",
      "LibraryName": "5）卫生间（非整体卫浴，异层排水）结构标高为客厅结构面标高h-50mm；"
    },
    {
      "1": "155",
      "CateName": "总包向室内精装修单位移交土建精装修工作面",
      "LibraryName": "6）厨房结构标高为建筑标高H-50mm(非薄贴）,H-20mm(薄贴）；"
    },
    {
      "1": "156",
      "CateName": "总包向室内精装修单位移交土建精装修工作面",
      "LibraryName": "7）卧室标高为建筑标高H-50mm(非薄贴）,H-20mm(薄贴）；"
    },
    {
      "1": "157",
      "CateName": "总包向室内精装修单位移交土建精装修工作面",
      "LibraryName": "8）客厅结构标高为建筑标高H-50mm(非薄贴）,H-20mm(薄贴）；"
    },
    {
      "1": "158",
      "CateName": "总包向室内精装修单位移交土建精装修工作面",
      "LibraryName": "9）阳台结构标高为建筑标高H-80mm；"
    },
    {
      "1": "159",
      "CateName": "总包向室内精装修单位移交土建精装修工作面",
      "LibraryName": "10）一米线：主要复核铺贴完成面与推拉门下滑及小阳台门是否冲突，复核推拉门下滑完成面应高于阳台门下框完成面。"
    },
    {
      "1": "160",
      "CateName": "总包向室内精装修单位移交土建精装修工作面",
      "LibraryName": "11）对所有室内墙面进行实测实量检验：内墙大面垂直度与平整度[0，4]mm）踢脚线平整度[0,3]mm）门贴脸平整度[0,3]mm）开关面板平整度[0,3]mm顶板水平度[0，10]mm）方正度[0，10]mm）木地板基层地面平整度[0,3]mm）开间进深[0，10]mm）阴阳角[0,4]mm）窗边墙大小头[0,3]mm）入户门框正面垂直度[0，3]mm；同一室内底盒标高差[0，10]mm）座便坑距偏差[0，15]mm）户内门洞尺寸偏差[-10，10]mm。"
    },
    {
      "1": "161",
      "CateName": "总包向室内精装修单位移交土建精装修工作面",
      "LibraryName": "12）门洞尺寸：门洞高度）宽度，厚度由专业分包办理移交，贴砖面需对精装修规定交底保证厚度一致及高度。"
    },
    {
      "1": "162",
      "CateName": "总包向室内精装修单位移交土建精装修工作面",
      "LibraryName": "13）阳露台：阳台线条顺直）滴水线顺直）管根处平整，由外墙单位自行移交。"
    },
    {
      "1": "163",
      "CateName": "总包向室内精装修单位移交土建精装修工作面",
      "LibraryName": "14）抹灰空鼓：总包进行整体排查整改。而后精装修进行二次排查，体现在一户一表中。"
    },
    {
      "1": "164",
      "CateName": "总包向室内精装修单位移交土建精装修工作面",
      "LibraryName": "15）天花整改：主要是模板之间拼缝处高低差抹平。吊模铁片）底盒铁钉切除后进行防锈处理。"
    },
    {
      "1": "165",
      "CateName": "总包向室内精装修单位移交土建精装修工作面",
      "LibraryName": "16）木地板地面：墙脚处超高，地面落地灰处理。"
    },
    {
      "1": "166",
      "CateName": "总包向室内精装修单位移交土建精装修工作面",
      "LibraryName": "17）卫生间基层处理：基层空鼓）超高进行打凿处理。重新处理基层（保证有坡度，向地漏方向找坡）。"
    },
    {
      "1": "167",
      "CateName": "总包向室内精装修单位移交土建精装修工作面",
      "LibraryName": "18）烟道大小：按照精装修图平立面效果，确定好烟道尺寸，确保橱柜安装效果。"
    },
    {
      "1": "168",
      "CateName": "总包向室内精装修单位移交土建精装修工作面",
      "LibraryName": "19）厨房，卫生间：阳台防水高度，厚度的规定及闭水要求（按闭水举牌验收为准）。"
    },
    {
      "1": "169",
      "CateName": "总包向室内精装修单位移交土建精装修工作面",
      "LibraryName": "20）户内门及入户门单位必须对门洞尺寸进行100%实测汇总数据到甲方，再由项目部统一定尺（偏差过大发函由总包修补）；门洞边做好复核（交接检），跨门洞偏差（0-1mm），门洞厚度偏差（0-1mm）方可安装门套线安装（木作单位对班组做好交底）。"
    },
    {
      "1": "170",
      "CateName": "总包向室内精装修单位移交土建精装修工作面",
      "LibraryName": "21）门槛结构应低于铝合金下滑3cm，距墙2cm。"
    },
    {
      "1": "171",
      "CateName": "总包向室内精装修单位移交土建精装修工作面",
      "LibraryName": "22）阳台推拉门框安装标高应以精装单位一米线核对确认后方可安装。"
    },
    {
      "1": "172",
      "CateName": "机电向室内精装修单位移交机电室内精装修工作面",
      "LibraryName": "1）天花墙面多余线盒封堵;"
    },
    {
      "1": "173",
      "CateName": "机电向室内精装修单位移交机电室内精装修工作面",
      "LibraryName": "2） 线盒高差、入墙深度、机电点位标高等符合要求;"
    },
    {
      "1": "174",
      "CateName": "机电向室内精装修单位移交机电室内精装修工作面",
      "LibraryName": "3）电缆电线，吊顶内机电安装、给水打压，排水系统通水通球工作已完成，且功能正常。"
    },
    {
      "1": "175",
      "CateName": "机电向室内精装修单位移交机电室内精装修工作面",
      "LibraryName": "4）垃圾清理完成。"
    },
    {
      "1": "176",
      "CateName": "机电向室内精装修单位移交机电室内精装修工作面",
      "LibraryName": "5）水管：水管打压无漏点按一户一表记录后移交。"
    },
    {
      "1": "177",
      "CateName": "机电向室内精装修单位移交机电室内精装修工作面",
      "LibraryName": "6）用电线管：线管穿线后移交，同步记录于一户一表。"
    },
    {
      "1": "178",
      "CateName": "总包/精装修单位向木地板单位移交木地板工作面",
      "LibraryName": "1) 地面平整度及地面水平度极差符合集团综合评估要求，砂浆找平层按照≤4mm，细石混凝土按照≤5mm，地面水平度极差≤10mm；"
    },
    {
      "1": "179",
      "CateName": "总包/精装修单位向木地板单位移交木地板工作面",
      "LibraryName": "2) 地面观感质量良好，无强度足够，不翻砂，无空鼓，裂缝修补"
    },
    {
      "1": "180",
      "CateName": "总包/精装修单位向木地板单位移交木地板工作面",
      "LibraryName": "3) 地面无腻子、油漆等精装修材料污染；"
    },
    {
      "1": "181",
      "CateName": "总包/精装修单位向木地板单位移交木地板工作面",
      "LibraryName": "4) 精装修垃圾清理完成。"
    },
    {
      "1": "182",
      "CateName": "木地板单位向精装修移交木地板完工工作面",
      "LibraryName": "1）木地板及踢脚线已按照设计及规范要求施工完毕；"
    },
    {
      "1": "183",
      "CateName": "木地板单位向精装修移交木地板完工工作面",
      "LibraryName": "2）木地板平整度、极差等符合要求；"
    },
    {
      "1": "184",
      "CateName": "木地板单位向精装修移交木地板完工工作面",
      "LibraryName": "3）木地板无明显色差，细部处理合理，无起翘、异响、爆灰等情况；"
    },
    {
      "1": "185",
      "CateName": "木地板单位向精装修移交木地板完工工作面",
      "LibraryName": "4）木地板已经完成成品保护。"
    },
    {
      "1": "186",
      "CateName": "总包单位向入户门单位移交入户门安装工作面",
      "LibraryName": "1) 入户门单位与总包单位提前沟通门缩尺尺寸，入户门单位核对门口尺寸是否符合安装要求；"
    },
    {
      "1": "187",
      "CateName": "总包单位向入户门单位移交入户门安装工作面",
      "LibraryName": "2) 室内地面施工完成，并且符合安装条件；"
    },
    {
      "1": "188",
      "CateName": "总包单位向入户门单位移交入户门安装工作面",
      "LibraryName": "3) 门洞是否按照要求预留预制块；"
    },
    {
      "1": "189",
      "CateName": "总包单位向入户门单位移交入户门安装工作面",
      "LibraryName": "4) 公共部位地面砖粘贴完成，地面砖标高与防盗门底槛标高一致；如有公共部位墙面砖，墙面砖粘贴完成，并且墙面垂直、平整符合规范要求，门口部位按照门口尺寸收齐；"
    },
    {
      "1": "190",
      "CateName": "总包单位向入户门单位移交入户门安装工作面",
      "LibraryName": "5) 总包单位提供防盗门安装标高控制线，并且控制线准确、清晰。"
    },
    {
      "1": "191",
      "CateName": "入户门单位向总包单位或精装修单位移交入户门完工工作面",
      "LibraryName": "1) 入户门已按照图纸及设计要求安装完成；"
    },
    {
      "1": "192",
      "CateName": "入户门单位向总包单位或精装修单位移交入户门完工工作面",
      "LibraryName": "2) 门框安装牢固、垂直；"
    },
    {
      "1": "193",
      "CateName": "入户门单位向总包单位或精装修单位移交入户门完工工作面",
      "LibraryName": "3) 门扇及门框完成满包成品保护；"
    },
    {
      "1": "194",
      "CateName": "入户门单位向总包单位或精装修单位移交入户门完工工作面",
      "LibraryName": "4) 门扇留缝均匀顺直、开启灵活、闭关严密；"
    },
    {
      "1": "195",
      "CateName": "入户门单位向总包单位或精装修单位移交入户门完工工作面",
      "LibraryName": "5) 门框及扇表面颜色均匀、无色差、无划痕、无敲打痕迹等缺陷。"
    },
    {
      "1": "196",
      "CateName": "精装修/总包向户内门单位移交户内门安装工作面",
      "LibraryName": "1) 精装修室内地面砖施工完成，并且符合安装条件；"
    },
    {
      "1": "197",
      "CateName": "精装修/总包向户内门单位移交户内门安装工作面",
      "LibraryName": "2) 总包洞口尺寸高度、宽度是否满足安装要求；"
    },
    {
      "1": "198",
      "CateName": "精装修/总包向户内门单位移交户内门安装工作面",
      "LibraryName": "3) 总包门洞是否按照要求预留预制块；"
    },
    {
      "1": "199",
      "CateName": "精装修/总包向户内门单位移交户内门安装工作面",
      "LibraryName": "4) 精装修单位提高标高控制线，并且控制线准确、清晰。"
    },
    {
      "1": "200",
      "CateName": "户内门单位向精装修单位移交户内门完工工作面",
      "LibraryName": "1) 户内门已按照图纸及设计要求安装完成；"
    },
    {
      "1": "201",
      "CateName": "户内门单位向精装修单位移交户内门完工工作面",
      "LibraryName": "2) 门框安装牢固、垂直；"
    },
    {
      "1": "202",
      "CateName": "户内门单位向精装修单位移交户内门完工工作面",
      "LibraryName": "3) 门扇留缝均匀顺直、开启灵活、闭关严密；"
    },
    {
      "1": "203",
      "CateName": "户内门单位向精装修单位移交户内门完工工作面",
      "LibraryName": "4) 五金件、门框及扇表面颜色均匀、无色差、无划痕、无敲打痕迹等缺陷；"
    },
    {
      "1": "204",
      "CateName": "户内门单位向精装修单位移交户内门完工工作面",
      "LibraryName": "5) 门扇与门框及地面缝隙不均匀、底缝水平；"
    },
    {
      "1": "205",
      "CateName": "户内门单位向精装修单位移交户内门完工工作面",
      "LibraryName": "6) 门框与墙体无缝隙；"
    },
    {
      "1": "206",
      "CateName": "户内门单位向精装修单位移交户内门完工工作面",
      "LibraryName": "7) 门扇及门框完成满包成品保护。"
    },
    {
      "1": "207",
      "CateName": "橱柜单位向精装修单位移交橱柜完工安装工作面",
      "LibraryName": "1) 橱柜表面无划痕、碰伤、油漆均匀无色差、碰伤等缺陷；"
    },
    {
      "1": "208",
      "CateName": "橱柜单位向精装修单位移交橱柜完工安装工作面",
      "LibraryName": "2) 安装牢固位置及尺寸大小符合设计要求，收边打胶饱满，顺直连续；"
    },
    {
      "1": "209",
      "CateName": "橱柜单位向精装修单位移交橱柜完工安装工作面",
      "LibraryName": "3) 柜门方正平直，门扇连接牢固、留缝均匀顺直、开启灵活、关闭严密无倒翘；"
    },
    {
      "1": "210",
      "CateName": "橱柜单位向精装修单位移交橱柜完工安装工作面",
      "LibraryName": "4) 给排水管道施工完成，且无渗漏；"
    },
    {
      "1": "211",
      "CateName": "橱柜单位向精装修单位移交橱柜完工安装工作面",
      "LibraryName": "5) 五金配件安装完成；"
    },
    {
      "1": "212",
      "CateName": "橱柜单位向精装修单位移交橱柜完工安装工作面",
      "LibraryName": "6) 橱柜及台面完成成品保护；"
    },
    {
      "1": "213",
      "CateName": "橱柜单位向精装修单位移交橱柜完工安装工作面",
      "LibraryName": "7) 未造成其他单位的成品破坏。"
    },
    {
      "1": "214",
      "CateName": "精装修单位向橱柜单位移交橱柜安装工作面",
      "LibraryName": "1) 地砖、墙砖全部完成；"
    },
    {
      "1": "215",
      "CateName": "精装修单位向橱柜单位移交橱柜安装工作面",
      "LibraryName": "2) 墙砖空鼓整改完成；"
    },
    {
      "1": "216",
      "CateName": "精装修单位向橱柜单位移交橱柜安装工作面",
      "LibraryName": "3) 天花吊顶完成；"
    },
    {
      "1": "217",
      "CateName": "精装修单位向橱柜单位移交橱柜安装工作面",
      "LibraryName": "4) 厨房空间能满足橱柜安装要求；"
    },
    {
      "1": "218",
      "CateName": "精装修单位向橱柜单位移交橱柜安装工作面",
      "LibraryName": "5) 机电单位穿线完成，点位定位准确；"
    },
    {
      "1": "219",
      "CateName": "精装修单位向橱柜单位移交橱柜安装工作面",
      "LibraryName": "6) 墙地砖成品保护完成。"
    },
    {
      "1": "220",
      "CateName": "橱柜单位向机电单位移交橱柜完工安装工作面",
      "LibraryName": "1）柜体全部安装完成，固定；"
    },
    {
      "1": "221",
      "CateName": "橱柜单位向机电单位移交橱柜完工安装工作面",
      "LibraryName": "2）星盆（洗菜盆安装完毕）；"
    },
    {
      "1": "222",
      "CateName": "橱柜单位向机电单位移交橱柜完工安装工作面",
      "LibraryName": "3）橱柜角阀、排水管位置开孔大小正确，确保角阀、排水管装饰盖装完后，不会漏缝；"
    },
    {
      "1": "223",
      "CateName": "橱柜单位向机电单位移交橱柜完工安装工作面",
      "LibraryName": "4）开关插座面板开孔大小正确，确保开关插座面板装完后，不会漏缝;"
    },
    {
      "1": "224",
      "CateName": "橱柜单位向机电单位移交橱柜完工安装工作面",
      "LibraryName": "5）橱柜及台面完成成品保护；"
    },
    {
      "1": "225",
      "CateName": "橱柜单位向机电单位移交橱柜完工安装工作面",
      "LibraryName": "6）未造成其他单位的成品破坏。"
    },
    {
      "1": "226",
      "CateName": "精装修/机电单位向收纳系统安装单位移交收纳系统安装工作面",
      "LibraryName": "1）机电穿线完成、电线回路通畅，点位定位准确；"
    },
    {
      "1": "227",
      "CateName": "精装修/机电单位向收纳系统安装单位移交收纳系统安装工作面",
      "LibraryName": "2）地砖、墙砖（湿作业）及成品全部完成；"
    },
    {
      "1": "228",
      "CateName": "精装修/机电单位向收纳系统安装单位移交收纳系统安装工作面",
      "LibraryName": "3）柜体安装空间尺寸无误；"
    },
    {
      "1": "229",
      "CateName": "精装修/机电单位向收纳系统安装单位移交收纳系统安装工作面",
      "LibraryName": "4）第一遍面漆完成（或底漆完成）。"
    },
    {
      "1": "230",
      "CateName": "收纳系统单位向机电单位移交收纳系统完工工作面",
      "LibraryName": "1）柜体全部安装完成，固定；"
    },
    {
      "1": "231",
      "CateName": "收纳系统单位向机电单位移交收纳系统完工工作面",
      "LibraryName": "2）开关插座面板（包括电箱面板）开孔正确，确保开关插座面板（包括电箱面板）装完后，不会漏缝；"
    },
    {
      "1": "232",
      "CateName": "收纳系统单位向机电单位移交收纳系统完工工作面",
      "LibraryName": "3）收纳系统无破坏、无划痕；"
    },
    {
      "1": "233",
      "CateName": "收纳系统单位向机电单位移交收纳系统完工工作面",
      "LibraryName": "4）未造成其他单位的成品保护破坏。"
    },
    {
      "1": "234",
      "CateName": "收纳系统单位向精装单位移交收纳系统完工工作面",
      "LibraryName": "1）柜体全部安装完成，固定；"
    },
    {
      "1": "235",
      "CateName": "收纳系统单位向精装单位移交收纳系统完工工作面",
      "LibraryName": "2）收口线条安装完毕；"
    },
    {
      "1": "236",
      "CateName": "收纳系统单位向精装单位移交收纳系统完工工作面",
      "LibraryName": "3）五金配件安装完成；"
    },
    {
      "1": "237",
      "CateName": "收纳系统单位向精装单位移交收纳系统完工工作面",
      "LibraryName": "4）成品保护完成；"
    },
    {
      "1": "238",
      "CateName": "收纳系统单位向精装单位移交收纳系统完工工作面",
      "LibraryName": "5）未造成其他单位成品保护破坏。"
    },
    {
      "1": "239",
      "CateName": "总包单位向消防单位移交消防工程工作面",
      "LibraryName": "1) 主包单位在主体结构阶段为消防预留孔洞及预埋套管的尺寸、位置、数量符合设计及规范要求；"
    },
    {
      "1": "240",
      "CateName": "总包单位向消防单位移交消防工程工作面",
      "LibraryName": "2) 主包单位提供消防管道及设备安装所需标高的基准点，并经项目工程团队、监理单位、主包单位、消防单位共同确认主包单位提供基准点的准确性；"
    },
    {
      "1": "241",
      "CateName": "总包单位向消防单位移交消防工程工作面",
      "LibraryName": "3) 消防安装部位主体工程质量符合设计规范及消防安装要求；"
    },
    {
      "1": "242",
      "CateName": "总包单位向消防单位移交消防工程工作面",
      "LibraryName": "4) 消防设备安装所需基础及预埋件质量、位置、尺寸符合设计规范要求；"
    },
    {
      "1": "243",
      "CateName": "总包单位向消防单位移交消防工程工作面",
      "LibraryName": "5) 主包单位提供的水源接驳点及电源接驳点满足消防施工条件；"
    },
    {
      "1": "244",
      "CateName": "总包单位向消防单位移交消防工程工作面",
      "LibraryName": "6) 消防施工场地范围内主包单位的垃圾及临时施工设施清理完成；"
    },
    {
      "1": "245",
      "CateName": "总包单位向消防单位移交消防工程工作面",
      "LibraryName": "7) 消防施工中涉及到的安全防护设施齐备到位；"
    },
    {
      "1": "246",
      "CateName": "总包单位向消防单位移交消防工程工作面",
      "LibraryName": "8）消防所需的垂直运输机械运行正常。"
    },
    {
      "1": "247",
      "CateName": "总包单位向通风单位移交通风工程工作面",
      "LibraryName": "1) 主包单位在主体结构阶段为通风预留孔洞及预埋套管的尺寸、位置、数量符合设计及规范要求；"
    },
    {
      "1": "248",
      "CateName": "总包单位向通风单位移交通风工程工作面",
      "LibraryName": "2) 主包单位提供通风管道及设备安装所需标高的基准点，并经项目工程团队、监理单位、主包单位、消防单位共同确认主包单位提供基准点的准确性；"
    },
    {
      "1": "249",
      "CateName": "总包单位向通风单位移交通风工程工作面",
      "LibraryName": "3) 通风安装部位主体工程质量符合设计规范及通风安装要求；"
    },
    {
      "1": "250",
      "CateName": "总包单位向通风单位移交通风工程工作面",
      "LibraryName": "4) 通风设备安装所需基础及预埋件质量、位置、尺寸符合设计规范要求；"
    },
    {
      "1": "251",
      "CateName": "总包单位向通风单位移交通风工程工作面",
      "LibraryName": "5) 主包单位提供的水源接驳点及电源接驳点满足通风施工条件；"
    },
    {
      "1": "252",
      "CateName": "总包单位向通风单位移交通风工程工作面",
      "LibraryName": "6) 通风施工场地范围内主包单位的垃圾及临时施工设施清理完成；"
    },
    {
      "1": "253",
      "CateName": "总包单位向通风单位移交通风工程工作面",
      "LibraryName": "7) 通风施工中涉及到的安全防护设施齐备到位。"
    },
    {
      "1": "254",
      "CateName": "总包单位向通风单位移交通风工程工作面",
      "LibraryName": "8) 通风所需的垂直运输机械运行正常。"
    },
    {
      "1": "255",
      "CateName": "总包单位向电梯单位移交电梯工程工作面",
      "LibraryName": "1) 混凝土主体封顶并全部拆模完成，如电梯井道需进行砌筑施工的，需所有电梯井道砌筑抹灰工作全部完成；"
    },
    {
      "1": "256",
      "CateName": "总包单位向电梯单位移交电梯工程工作面",
      "LibraryName": "2) 电梯井道内防护设施全部拆除完成并清理干净，保留电梯口防护；"
    },
    {
      "1": "257",
      "CateName": "总包单位向电梯单位移交电梯工程工作面",
      "LibraryName": "3) 电梯井道内对拉螺栓、钢筋等出墙面构件清除干净；"
    },
    {
      "1": "258",
      "CateName": "总包单位向电梯单位移交电梯工程工作面",
      "LibraryName": "4) 电梯基坑清理完成，防水工程完成，无积水；"
    },
    {
      "1": "259",
      "CateName": "总包单位向电梯单位移交电梯工程工作面",
      "LibraryName": "5) 电梯机房砌筑、抹灰、地面全部完成，机房预留孔洞正确，设备基础与设计相符，机房屋面经试水不渗漏，机房门安装完成，并能锁门（若机房门为甲分包工程，由甲方工程师负责协调）；"
    },
    {
      "1": "260",
      "CateName": "总包单位向电梯单位移交电梯工程工作面",
      "LibraryName": "6) 每层电梯门口前标高控制线准确、清晰；"
    },
    {
      "1": "261",
      "CateName": "总包单位向电梯单位移交电梯工程工作面",
      "LibraryName": "7) 电梯安装单位须对所有电梯洞口尺寸、井道尺寸、呼叫底盒位置尺寸、吊筋位置等进行详细复核，电梯门洞有可靠安装连接点；"
    },
    {
      "1": "262",
      "CateName": "总包单位向电梯单位移交电梯工程工作面",
      "LibraryName": "8) 电梯门口施工完成高度须经过甲方、监理、主包单位、公共部位精装修单位、电梯安装单位共同确定，并留有各方签字确认的文字依据；"
    },
    {
      "1": "263",
      "CateName": "总包单位向电梯单位移交电梯工程工作面",
      "LibraryName": "9) 由主包单位提供安装、调试电源接驳点；"
    },
    {
      "1": "264",
      "CateName": "总包单位向电梯单位移交电梯工程工作面",
      "LibraryName": "10) 电梯井道门口弹出装饰完成线。"
    },
    {
      "1": "265",
      "CateName": "电梯向总包单位移交电梯安装完成后收口工作面",
      "LibraryName": "1) 电梯井道内、电梯基坑、电梯机房相关电梯设备已安装完成；"
    },
    {
      "1": "266",
      "CateName": "电梯向总包单位移交电梯安装完成后收口工作面",
      "LibraryName": "2) 电梯门安装固定稳固，未造成墙体破坏；"
    },
    {
      "1": "267",
      "CateName": "电梯向总包单位移交电梯安装完成后收口工作面",
      "LibraryName": "3) 电梯井道垃圾、电梯机房垃圾清理完毕。"
    },
    {
      "1": "268",
      "CateName": "总包单位向车库门安装单位移交车库门安装工作面",
      "LibraryName": "1) 车库门门口尺寸符合图纸设计要求；"
    },
    {
      "1": "269",
      "CateName": "总包单位向车库门安装单位移交车库门安装工作面",
      "LibraryName": "2) 车库门门口四周无影响车库门安装的设备设施；"
    },
    {
      "1": "270",
      "CateName": "总包单位向车库门安装单位移交车库门安装工作面",
      "LibraryName": "3) 墙面补洞及抹灰施工完成，并且垂直、平整符合规范要求；"
    },
    {
      "1": "271",
      "CateName": "总包单位向车库门安装单位移交车库门安装工作面",
      "LibraryName": "4) 总包单位提供施工用电；"
    },
    {
      "1": "272",
      "CateName": "总包单位向车库门安装单位移交车库门安装工作面",
      "LibraryName": "5) 垃圾与堆放材料清理完毕；"
    },
    {
      "1": "273",
      "CateName": "总包单位向车库门安装单位移交车库门安装工作面",
      "LibraryName": "6) 地面施工完成；"
    },
    {
      "1": "274",
      "CateName": "总包单位向车库门安装单位移交车库门安装工作面",
      "LibraryName": "7) 移交“三线”。"
    },
    {
      "1": "275",
      "CateName": "总包单位向土方单位移交土方回填工作面",
      "LibraryName": "1) 施工范围内地上附属设施拆除完毕；"
    },
    {
      "1": "276",
      "CateName": "总包单位向土方单位移交土方回填工作面",
      "LibraryName": "2) 施工范围内塔吊基础、硬化路面破除、清理完毕；"
    },
    {
      "1": "277",
      "CateName": "总包单位向土方单位移交土方回填工作面",
      "LibraryName": "3) 总包单位需提供室外标高控制点，并进行复核；"
    },
    {
      "1": "278",
      "CateName": "总包单位向土方单位移交土方回填工作面",
      "LibraryName": "4) 地下临时水电管线布置图确认并移交；"
    },
    {
      "1": "279",
      "CateName": "总包单位向土方单位移交土方回填工作面",
      "LibraryName": "5) 按设计标高完成室外土方回填工作并进行复测；"
    },
    {
      "1": "280",
      "CateName": "总包单位向土方单位移交土方回填工作面",
      "LibraryName": "6) 其它分包单位应将施工范围内材料清理完毕。"
    },
    {
      "1": "281",
      "CateName": "土方单位向室外市政管线/园林绿化施工单位移交室外市政及综合管线工作面",
      "LibraryName": "1) 按设计及甲方要求标高完成室外土方回填工作并进行复测；"
    },
    {
      "1": "282",
      "CateName": "土方单位向室外市政管线/园林绿化施工单位移交室外市政及综合管线工作面",
      "LibraryName": "2) 回填土料及压实系数符合设计及规范要求；"
    },
    {
      "1": "283",
      "CateName": "土方单位向室外市政管线/园林绿化施工单位移交室外市政及综合管线工作面",
      "LibraryName": "3) 表面平整度符合要求。"
    },
    {
      "1": "284",
      "CateName": "室外市政/管线施工单位向园林景观单位移交景观绿化工作面",
      "LibraryName": "1) 室外市政及综合管线工程完成施工，并且符合图纸设计要求；"
    },
    {
      "1": "285",
      "CateName": "室外市政/管线施工单位向园林景观单位移交景观绿化工作面",
      "LibraryName": "2) 所有外网井完成，所有井盖覆盖完毕，标高符合图纸设计要求，管网回填土进行分层碾压，避免沉降造成园区景观道路破坏。"
    },
    {
      "1": "286",
      "CateName": "室外市政/管线施工单位向园林景观单位移交景观绿化工作面",
      "LibraryName": "3) 强电箱变基础施工完毕，绿化地形可以与强电箱变进行交接；"
    },
    {
      "1": "287",
      "CateName": "室外市政/管线施工单位向园林景观单位移交景观绿化工作面",
      "LibraryName": "4) 各种材料堆放场地全部清理完毕，具备施工条件；"
    },
    {
      "1": "288",
      "CateName": "室外市政/管线施工单位向园林景观单位移交景观绿化工作面",
      "LibraryName": "5) 所有外网管井全部有明显标记，防止后期施工破坏后无法找到。"
    },
    {
      "1": "289",
      "CateName": "通用工作面交接",
      "LibraryName": "具备移交条件"
    }
  ]
}